Metadata-Version: 2.1
Name: plotai
Version: 0.0.5
Summary: Create plots in Python with AI
Home-page: https://github.com/mljar/plotai
Author: MLJAR Sp. z o.o.
Author-email: contact@mljar.com
License: Apache 2.0
Keywords: plot,visualization,charts,matplotlib,llm,openai,mljar
Platform: UNKNOWN
Classifier: Programming Language :: Python
Classifier: Programming Language :: Python :: 3.7
Classifier: Programming Language :: Python :: 3.8
Classifier: Programming Language :: Python :: 3.9
Classifier: Programming Language :: Python :: 3.10
Classifier: Programming Language :: Python :: 3.11
Requires-Python: >=3.7.1
